mcdc_convergence_test/__init__.py
mcdc_convergence_test/benchmarks.hdf5
mcdc_convergence_test/main.py
mcdc_convergence_test/run.py
mcdc_convergence_test-0.0.4.dist-info/METADATA
mcdc_convergence_test-0.0.4.dist-info/WHEEL
mcdc_convergence_test-0.0.4.dist-info/licenses/LICENSE
mcdc_convergence_test-0.0.4.dist-info/RECORD
