Metadata-Version: 2.3
Name: mcdc_convergence_test
Version: 0.0.4
Summary: Tests certain mcdc functionality convergence to semi-analytical solutions provided by William Bennett
Author-email: Aidan Murray <amurra24@nd.edu>
License-File: LICENSE
Classifier: License :: OSI Approved :: MIT License
Classifier: Operating System :: OS Independent
Classifier: Programming Language :: Python :: 3
Requires-Python: >=3.8
